pearun/__init__.py
pearun/__main__.py
pearun/exceptions.py
pearun/pearunfile.py
pearun-1.0.0.dist-info/LICENSE
pearun-1.0.0.dist-info/METADATA
pearun-1.0.0.dist-info/WHEEL
pearun-1.0.0.dist-info/entry_points.txt
pearun-1.0.0.dist-info/top_level.txt
pearun-1.0.0.dist-info/RECORD
