Metadata-Version: 2.1
Name: pearun
Version: 1.0.0
Summary: A simple utility to run user defined commands
Home-page: https://github.com/Krakenus/pearun
Author: Milan Vlasák
Author-email: krakenus02@gmail.com
License: MIT
Platform: UNKNOWN
Classifier: Programming Language :: Python :: 3.6
Classifier: Programming Language :: Python :: 3.7
Classifier: Programming Language :: Python :: 3.8
Classifier: License :: OSI Approved :: MIT License
Classifier: Operating System :: OS Independent
Requires-Python: >=3.6
Requires-Dist: click
